README.md
setup.py
tzevaadom/__init__.py
tzevaadom/cities.json
tzevaadom/tzevaadom.py
tzevaadom.egg-info/PKG-INFO
tzevaadom.egg-info/SOURCES.txt
tzevaadom.egg-info/dependency_links.txt
tzevaadom.egg-info/top_level.txt