Metadata-Version: 2.1
Name: tzevaadom
Version: 1.1
Summary: A Python library for Pikud Haoref's unofficial rocket alert API.
Home-page: https://github.com/itaiguli/
Author: Itai Guli
Author-email: app.redalert@gmail.com
License: MIT
Download-URL: https://github.com/itaiguli/python-pikudHaoref-api/archive/1.0.tar.gz
Keywords: tzevaadom,pikud,oref,redalert,rocket
Platform: UNKNOWN
Classifier: Development Status :: 3 - Alpha
Classifier: Intended Audience :: Developers
Classifier: Topic :: Software Development :: Build Tools
Classifier: License :: OSI Approved :: MIT License
Classifier: Programming Language :: Python :: 3
Classifier: Programming Language :: Python :: 3.4
Classifier: Programming Language :: Python :: 3.5
Classifier: Programming Language :: Python :: 3.6
Classifier: Programming Language :: Python :: 3.7
Classifier: Programming Language :: Python :: 3.8
